src/__init__.py
src/always_list_field.py
src/test_always_list_nested_field.py
always_list_field-1.0.0.dist-info/LICENSE
always_list_field-1.0.0.dist-info/METADATA
always_list_field-1.0.0.dist-info/WHEEL
always_list_field-1.0.0.dist-info/top_level.txt
always_list_field-1.0.0.dist-info/RECORD
