Metadata-Version: 2.1
Name: always-list-field
Version: 1.0.0
Summary: Ensure that your schema field will be a list
Home-page: https://github.com/szymansd/marshmallow-always-list-field
Author: Dominik Szymanski
Author-email: Dominik Szymanski <info@realpython.com>
License: MIT License
Project-URL: Homepage, https://github.com/szymansd/marshmallow-always-list-field
Keywords: marshmallow,list,fields
Classifier: License :: OSI Approved :: MIT License
Classifier: Programming Language :: Python
Classifier: Programming Language :: Python :: 3
Requires-Python: >=3.8
License-File: LICENSE
Requires-Dist: marshmallow
Provides-Extra: dev
Requires-Dist: black ; extra == 'dev'
Requires-Dist: bumpver ; extra == 'dev'
Requires-Dist: isort ; extra == 'dev'
Requires-Dist: pip-tools ; extra == 'dev'
Requires-Dist: pytest ; extra == 'dev'
Requires-Dist: marshmallow ; extra == 'dev'
